pyceg/__init__.py
pyceg/cli.py
pyceg/hello.py
pyceg/pypi.py
pyceg/Multiprocessor/CacheCoherence.py
pyceg/Multiprocessor/MESI.py
pyceg/Multiprocessor/MOESI.py
pyceg/Multiprocessor/MOSI.py
pyceg/Multiprocessor/MSI.py
pyceg/Multiprocessor/Main.py
pyceg/Multiprocessor/Operations.py
pyceg/Multiprocessor/Processor.py
pyceg/Multiprocessor/Protocol.py
pyceg/Multiprocessor/Simulation.py
pyceg/Multiprocessor/States.py
pyceg/Multiprocessor/Statistics.py
pyceg/Multiprocessor/VI_Write_Through.py
pyceg/Multiprocessor/__init__.py
pyceg-0.0.16.dist-info/LICENSE
pyceg-0.0.16.dist-info/METADATA
pyceg-0.0.16.dist-info/WHEEL
pyceg-0.0.16.dist-info/entry_points.txt
pyceg-0.0.16.dist-info/top_level.txt
pyceg-0.0.16.dist-info/RECORD
