Metadata-Version: 2.1
Name: pyceg
Version: 0.0.16
Summary: Nevin's Vision to bring Computer Architectures and Real Time Systems to Life Through Pythonic Implementations
Home-page: https://github.com/iDuckDark/PyNevin
Author: Nevin WS Ganesan
Author-email: PyNevin@idarkduck.com
License: Apache License 2.0
Platform: UNKNOWN
Requires-Dist: click
